achilles/__init__.py
achilles/model.py
snail_achilles-0.0.6.dist-info/METADATA
snail_achilles-0.0.6.dist-info/WHEEL
snail_achilles-0.0.6.dist-info/top_level.txt
snail_achilles-0.0.6.dist-info/RECORD
