Metadata-Version: 2.1
Name: snail-achilles
Version: 0.0.6
Summary: Model file manager
Home-page: https://git.woniubaoxian.com/ai/ai-achilles-service
Author: AngeloLi
Author-email: libiao_0303@live.com
License: UNKNOWN
Platform: UNKNOWN
Classifier: Programming Language :: Python :: 3
Classifier: Operating System :: OS Independent
Requires-Python: >=3.6
Requires-Dist: requests (>=2.23.0)
